maven/__init__.py
maven/async_models.py
maven/async_orchestrator.py
maven/cli.py
maven/collaborative.py
maven/consensus.py
maven/hallucination_detector.py
maven/models.py
maven/orchestrator.py
maven/py.typed
maven/roles.py
maven/tools.py
maven/utils.py
maven_protocol-0.2.0.dist-info/licenses/LICENSE
maven_protocol-0.2.0.dist-info/METADATA
maven_protocol-0.2.0.dist-info/WHEEL
maven_protocol-0.2.0.dist-info/entry_points.txt
maven_protocol-0.2.0.dist-info/top_level.txt
maven_protocol-0.2.0.dist-info/RECORD
